{
  "timetype": "time",
  "pensum": "90%",
  "entries": [],
  "tags": [
    {
      "id": 1,
      "name": "Betreuungsurlaub",
      "type": 1
    },
    {
      "id": 2,
      "name": "Schulung",
      "type": 2
    },
    {
      "id": 3,
      "name": "Ferien",
      "type": 1
    },
    {
      "id": 4,
      "name": "Administration",
      "type": 2
    },
    {
      "id": 5,
      "name": "Arztbeszch",
      "type": 2
    },
    {
      "id": 6,
      "name": "Bezahlte Absenz",
      "type": 1
    },
    {
      "id": 7,
      "name": "Projekt x",
      "type": 3
    },
    {
      "id": 8,
      "name": "Projekt y",
      "type": 3
    }
  ],
  "types": [
    {
      "id": 1,
      "name": "Projektleistung"
    },
    {
      "id": 2,
      "name": "Nicht-Projektleistung"
    },
    {
      "id": 3,
      "name": "duno what to call this one jet"
    }
  ]
}